README.md
setup.py
ie/__init__.py
ie/ac.py
ie/al.py
ie/am.py
ie/ap.py
ie/ba.py
ie/ce.py
ie/checking.py
ie/df.py
ie/es.py
ie/go.py
ie/ma.py
ie/mg.py
ie/ms.py
ie/mt.py
ie/pa.py
ie/pb.py
ie/pe.py
ie/pi.py
ie/pr.py
ie/rj.py
ie/rn.py
ie/ro.py
ie/rr.py
ie/rs.py
ie/sc.py
ie/se.py
ie/sp.py
ie/to.py
ie.egg-info/PKG-INFO
ie.egg-info/SOURCES.txt
ie.egg-info/dependency_links.txt
ie.egg-info/not-zip-safe
ie.egg-info/top_level.txt