Metadata-Version: 1.1
Name: ie
Version: 2.0.0
Summary: Validation of brazilian state registration numbers
Home-page: https://github.com/matheuscas/pyIE
Author: Matheus Cardoso
Author-email: matheus.mcas@gmail.com
License: MIT
Keywords: inscrição estadual inscricao estadual inscricoes estaduais inscrições estaduais validacao validação
Platform: UNKNOWN
Classifier: Development Status :: 5 - Production/Stable
Classifier: License :: OSI Approved :: MIT License
Classifier: Programming Language :: Python :: 2.7
Classifier: Programming Language :: Python :: 3.7
Classifier: Topic :: Software Development :: Libraries :: Python Modules
